aea/__init__.py
aea/__version__.py
aea/abstract_agent.py
aea/aea.py
aea/aea_builder.py
aea/agent.py
aea/agent_loop.py
aea/cli/__init__.py
aea/cli/__main__.py
aea/cli/add.py
aea/cli/add_key.py
aea/cli/build.py
aea/cli/config.py
aea/cli/core.py
aea/cli/create.py
aea/cli/delete.py
aea/cli/eject.py
aea/cli/fetch.py
aea/cli/fingerprint.py
aea/cli/freeze.py
aea/cli/generate.py
aea/cli/generate_key.py
aea/cli/generate_wealth.py
aea/cli/get_address.py
aea/cli/get_multiaddress.py
aea/cli/get_public_key.py
aea/cli/get_wealth.py
aea/cli/init.py
aea/cli/install.py
aea/cli/interact.py
aea/cli/issue_certificates.py
aea/cli/launch.py
aea/cli/list.py
aea/cli/local_registry_sync.py
aea/cli/login.py
aea/cli/logout.py
aea/cli/plugin.py
aea/cli/publish.py
aea/cli/push.py
aea/cli/register.py
aea/cli/registry/__init__.py
aea/cli/registry/add.py
aea/cli/registry/fetch.py
aea/cli/registry/login.py
aea/cli/registry/logout.py
aea/cli/registry/publish.py
aea/cli/registry/push.py
aea/cli/registry/registration.py
aea/cli/registry/settings.py
aea/cli/registry/utils.py
aea/cli/remove.py
aea/cli/remove_key.py
aea/cli/reset_password.py
aea/cli/run.py
aea/cli/scaffold.py
aea/cli/search.py
aea/cli/transfer.py
aea/cli/upgrade.py
aea/cli/utils/__init__.py
aea/cli/utils/click_utils.py
aea/cli/utils/config.py
aea/cli/utils/constants.py
aea/cli/utils/context.py
aea/cli/utils/decorators.py
aea/cli/utils/exceptions.py
aea/cli/utils/formatting.py
aea/cli/utils/generic.py
aea/cli/utils/loggers.py
aea/cli/utils/package_utils.py
aea/common.py
aea/components/__init__.py
aea/components/base.py
aea/components/loader.py
aea/components/utils.py
aea/configurations/__init__.py
aea/configurations/base.py
aea/configurations/constants.py
aea/configurations/data_types.py
aea/configurations/loader.py
aea/configurations/manager.py
aea/configurations/pypi.py
aea/configurations/schemas/aea-config_schema.json
aea/configurations/schemas/configurable_parts/base-custom_config.json
aea-1.2.5.dist-info/entry_points.txt
aea-1.2.5.dist-info/LICENSE
aea-1.2.5.dist-info/WHEEL
aea-1.2.5.dist-info/METADATA
aea-1.2.5.dist-info/RECORD
