Metadata-Version: 2.1
Name: aea
Version: 1.2.5
Summary: Autonomous Economic Agent framework
Home-page: https://github.com/fetchai/agents-aea
License: Apache-2.0
Author: Fetch.AI Limited
Requires-Python: >=3.8,<3.11
Classifier: Development Status :: 4 - Beta
Classifier: Environment :: Console
Classifier: Intended Audience :: Developers
Classifier: Intended Audience :: Education
Classifier: Intended Audience :: End Users/Desktop
Classifier: Intended Audience :: Information Technology
Classifier: Intended Audience :: Science/Research
Classifier: License :: OSI Approved :: Apache Software License
Classifier: Natural Language :: English
Classifier: Operating System :: MacOS
Classifier: Operating System :: Microsoft :: Windows
Classifier: Operating System :: Unix
Classifier: Programming Language :: Python :: 3
Classifier: Programming Language :: Python :: 3.8
Classifier: Programming Language :: Python :: 3.9
Classifier: Programming Language :: Python :: 3.10
Classifier: Programming Language :: Python :: 3.10
Classifier: Programming Language :: Python :: 3.8
Classifier: Programming Language :: Python :: 3.9
Classifier: Topic :: Communications
Classifier: Topic :: Internet
Classifier: Topic :: Scientific/Engineering
Classifier: Topic :: Scientific/Engineering :: Artificial Intelligence
Classifier: Topic :: Software Development
Classifier: Topic :: System
Provides-Extra: all
Provides-Extra: cli
Requires-Dist: base58 (>=1.0.3,<3.0.0)
Requires-Dist: click (>=8.0.0,<9.0.0); extra == "cli" or extra == "all"
Requires-Dist: ecdsa (>=0.15,<0.17.0)
Requires-Dist: importlib-metadata (>4,<5)
Requires-Dist: jsonschema (>=3.2.0,<5)
Requires-Dist: packaging (>=21.0,<22.0)
Requires-Dist: protobuf (>=3.19.4,<4)
Requires-Dist: pymultihash (==0.8.2)
Requires-Dist: python-dotenv (>=0.14.0,<0.18.0)
Requires-Dist: pywin32 (==303); sys_platform == "win32" or platform_system == "Windows"
Requires-Dist: pyyaml (>=4.2b1,<6.0)
Requires-Dist: requests (>=2.22.0,<3.0.0)
Requires-Dist: semver (>=2.9.1,<3.0.0)
